{
  "main": {
    "id": "f4cc2b7e56bf4af2",
    "type": "split",
    "children": [
      {
        "id": "e42bf22421bf0a60",
        "type": "tabs",
        "children": [
          {
            "id": "e1004c88167bda71",
            "type": "leaf",
            "state": {
              "type": "empty",
              "state": {},
              "icon": "lucide-file",
              "title": "Nova aba"
            }
          }
        ]
      }
    ],
    "direction": "vertical"
  },
  "left": {
    "id": "aff0a1b462e41725",
    "type": "split",
    "children": [
      {
        "id": "8e3b7e0b04e7a817",
        "type": "tabs",
        "children": [
          {
            "id": "a6996ec1e83b902f",
            "type": "leaf",
            "state": {
              "type": "file-explorer",
              "state": {
                "sortOrder": "alphabetical"
              },
              "icon": "lucide-folder-closed",
              "title": "Explorador de arquivos"
            }
          },
          {
            "id": "f79dbf25dba70d69",
            "type": "leaf",
            "state": {
              "type": "search",
              "state": {
                "query": "",
                "matchingCase": false,
                "explainSearch": false,
                "collapseAll": false,
                "extraContext": false,
                "sortOrder": "alphabetical"
              },
              "icon": "lucide-search",
              "title": "Procurar"
            }
          },
          {
            "id": "8a63945f67e590b8",
            "type": "leaf",
            "state": {
              "type": "bookmarks",
              "state": {},
              "icon": "lucide-bookmark",
              "title": "Marcadores"
            }
          }
        ]
      }
    ],
    "direction": "horizontal",
    "width": 300
  },
  "right": {
    "id": "6c2785dabf005015",
    "type": "split",
    "children": [
      {
        "id": "152dd54d415d1972",
        "type": "tabs",
        "children": [
          {
            "id": "ed5f0ccc351fff2a",
            "type": "leaf",
            "state": {
              "type": "backlink",
              "state": {
                "collapseAll": false,
                "extraContext": false,
                "sortOrder": "alphabetical",
                "showSearch": false,
                "searchQuery": "",
                "backlinkCollapsed": false,
                "unlinkedCollapsed": true
              },
              "icon": "links-coming-in",
              "title": "Backlinks"
            }
          },
          {
            "id": "eed3cf15c3c3ada7",
            "type": "leaf",
            "state": {
              "type": "outgoing-link",
              "state": {
                "linksCollapsed": false,
                "unlinkedCollapsed": true
              },
              "icon": "links-going-out",
              "title": "Links de saída"
            }
          },
          {
            "id": "5cbb2ffa655517dd",
            "type": "leaf",
            "state": {
              "type": "tag",
              "state": {
                "sortOrder": "frequency",
                "useHierarchy": true
              },
              "icon": "lucide-tags",
              "title": "Tags"
            }
          },
          {
            "id": "6f476314bb8cab3d",
            "type": "leaf",
            "state": {
              "type": "outline",
              "state": {},
              "icon": "lucide-list",
              "title": "Sumário"
            }
          }
        ]
      }
    ],
    "direction": "horizontal",
    "width": 300,
    "collapsed": true
  },
  "left-ribbon": {
    "hiddenItems": {
      "switcher:Abrir a troca rápida": false,
      "graph:Abrir visualização em gráfico": false,
      "canvas:Criar novo canvas": false,
      "daily-notes:Abrir a nota de hoje": false,
      "templates:Inserir modelo": false,
      "command-palette:Abrir paleta de comandos": false
    }
  },
  "active": "e1004c88167bda71",
  "lastOpenFiles": []
}